CHANGELOG
LICENSE
MANIFEST.in
README
examples
ez_setup.py
rdf
run_tests.py
setup.cfg
setup.py
examples/example.py
examples/swap_primer.py
rdf/__init__.py
rdf/_namespace.py
rdf/exceptions.py
rdf/graph.py
rdf/namespace.py
rdf/parser.py
rdf/plugin.py
rdf/query.py
rdf/serializer.py
rdf/store.py
rdf/term.py
rdf.egg-info/PKG-INFO
rdf.egg-info/SOURCES.txt
rdf.egg-info/dependency_links.txt
rdf.egg-info/top_level.txt
rdf/plugins/__init__.py
rdf/plugins/parsers/__init__.py
rdf/plugins/serializers/__init__.py
rdf/plugins/stores/__init__.py
rdf/tests/__init__.py
rdf/tests/test_equality.py
rdf/tests/test_graph.py