Metadata-Version: 1.0
Name: rdf
Version: 0.9a6
Summary: A pure Python package providing the core RDF constructs.
Home-page: http://rdflib.net/
Author: Daniel 'eikeon' Krech
Author-email: eikeon@eikeon.com
License: http://rdflib.net/latest/LICENSE
Platform: any
Classifier: Programming Language :: Python
Classifier: License :: OSI Approved :: BSD License
Classifier: Topic :: Software Development :: Libraries :: Python Modules
Classifier: Operating System :: OS Independent
Classifier: Natural Language :: English
